addci/__init__.py
addci/functions.py
addci-0.1.0.dist-info/METADATA
addci-0.1.0.dist-info/WHEEL
addci-0.1.0.dist-info/top_level.txt
addci-0.1.0.dist-info/RECORD
